README.md
pyproject.toml
src/picotalk/__init__.py
src/picotalk/client.py
src/picotalk/common.py
src/picotalk/server.py
src/picotalk.egg-info/PKG-INFO
src/picotalk.egg-info/SOURCES.txt
src/picotalk.egg-info/dependency_links.txt
src/picotalk.egg-info/entry_points.txt
src/picotalk.egg-info/requires.txt
src/picotalk.egg-info/top_level.txt
src/picotalk/audio/__init__.py
src/picotalk/audio/audio_processor.py
src/picotalk/audio/noise_removal.py
src/picotalk/audio/squelch.py
src/picotalk/transports/__init__.py
src/picotalk/transports/base.py
src/picotalk/transports/encrypted.py
src/picotalk/transports/packet.py
src/picotalk/transports/tcp.py
src/picotalk/transports/udp.py
src/picotalk/transports/websocket.py