Metadata-Version: 2.1
Name: picotalk
Version: 0.0.22
Summary: Simple voice call tool.
Author-email: "T. Kramer" <code@tkramer.ch>
License: AGPL-3.0-or-later
Project-URL: Homepage, https://codeberg.org/tok/picotalk
Project-URL: Repository, https://codeberg.org/tok/picotalk
Project-URL: Issue Tracker, https://codeberg.org/tok/picotalk/issues
Keywords: cmos,cell,characterization,vlsi,asic
Classifier: License :: OSI Approved :: GNU Affero General Public License v3 or later (AGPLv3+)
Classifier: Development Status :: 4 - Beta
Classifier: Programming Language :: Python :: 3.8
Classifier: Topic :: Communications :: Conferencing
Requires-Python: >=3.8
Requires-Dist: aiohttp
Requires-Dist: pyaudio
Requires-Dist: numpy
Requires-Dist: scipy
